{
  "slug": "watt",
  "titre": "Journal of James Watt Expedition to and from Timbo in 1794",
  "auteur": "Journal of James Watt Expedition to and from Timbo in 1794",
  "rubrique": "History",
  "annee": "1994",
  "editeur": "Edition and Introduction by Bruce L. Mouser African Studies Program. University of Wisconsin-Madison. 1994. 97 pages",
  "resume": "Journal of the voyage to Timbo from Sierra Leone by James Watt in 1793",
  "motsCles": [
    "Timbo",
    "Fuuta-Jalon",
    "Fouta-Diallon",
    "Labe",
    "Sierra-Leone",
    "England",
    "Islam",
    "Almami"
  ],
  "nbChapitres": 10,
  "liensExternes": [
    "http://www.webcote.net/",
    "http://www.webguine.site/etat/postcolonial/prefectures/boke/boke.html",
    "http://www.webguine.site/etat/postcolonial/prefectures/forekariya/fodekariya.html",
    "http://www.webguine.siteetat/postcolonial/prefectures/bofa/bofa.html"
  ],
  "chapitres": [
    {
      "id": "preface",
      "file": "preface.html",
      "titre": "Preface",
      "html": "<h2>Preface</h2>\n<p>In 1994 the James Watt journal of his travels to and from Timbo, the capital of\n     the Fula Empire in the Futa Jalon highlands of modern Guinea, will be two hundred\n     years old. Perhaps it is fitting that in its two-hundredth year, it finally\n     be printed in a script that is readable and available to scholars who will profit\n     from its contents. Watt, unfortunately, died an untimely death little more than\n     a year after his travels to Timbo in 1794, at the early age of 35 years, without\n     having polished his journal into publishable form. At the time of his death,\n     Watt and James Gray were planning a monumental challenge: an overland exploration\n     of West Africa from the coast to Timbuktu and from there to North Africa across\n     the Sahara. Others soon would attempt similar travels and follow their successes\n     with journals in published form. Surely Watt had like designs for his writings.\n     His traveling companion to Timbo, Matthew Winterbottom, likewise died an early\n     death, but Winterbottom's journal was used by his brother, Dr. Thomas Winterbottom,\n     who wrote and had published his own important two-volume An Account of the Native\n     Afticans in the Neighbourhood of Sierra Leone in 1803. Except for those few\n     scholars who sought out Watt's manuscript journal of the expedition to Timbo,\n     the only accessible version was that by Winterbottom; and Dr. Winterbottom was\n     clearly more interested in a description of the “native African” than\n     recording the attitudes of those who made the journey or their daily trials\n     and observations along the way.<br />\n     The only extant copy of Watt's record, itself\n     a copy of the original which in 1794 was deposited in the Secretary's Office\n     of Fort Thomton, the center of the Sierra Leone Company's activities in Freetown'\n     is in Rhodes House Library, Oxford. When this copy of the original was made\n     is unclear. It was written on both sides on foolscap paper. Whether at the time\n     of copying or later, page numbers were added on the first side. It is clear\n     that the copier had some difficulty in reading sections of the original document,\n     especially toward the end of the joumal. In several instances, the copier left\n     blank spaces in the text, presumably because words were either missing in the\n     original or undecipherable. In other cases the copier made mistakes and simply\n     crossed through the errors. In two instances the copier left large spaces and\n     in another place he indicated that something was unintelligible in the original\n     and that he subsequently omitted what he considered unimportant.<br />\n     I attempted to avoid these pitfalls, especially the latter. But some changes\n     were made in the manuscript. The copier (I will assume that the problems were\n     his) was generally an excellent speller, sometimes using words which I did not\n     know or recognize but using them correctly for his time. Words, such as “everything” and “anything,” were\n     in places divided and in others not; “ice” often became “ei;” and\n     words with double letters sometimes had them and sometimes not. The spelling\n     of Arabic and African names lacked consistency. In each case, I sought to follow\n     his spelling and use the expression “[sic]” sparingly.<br />\nCapitalization in this copy was typical of the late eighteenth century; one has the\nimpression that the author used capital letters for emphasis as well as to introduce\na sentence or a new thought. For sake of clarity for today's readers, I decided that\ncapitalization should be removed altogether, except for the beginning of sentences,\nfor proper names and titles, and for words to which a more formal addition appeared\nelsewhere in the text. Removing capitalization was not a major problem, partly because\nI was uncertain whether the copier intended for some letters to be taken as capital\nletters.<br />\nPunctuation did not seem to follow any particular stylistic or grammatical principles.\nWatt (i.e., the copier) clearly liked to use commas and dashes in his writing. Rather\nthan follow his forms exactly, I chose instead to delete dashes and to follow his\npunctuation only where it was useful in explaining the text. Generally I did not\nadd or delete punctuation, except where it was crucial; and where my addition might\nmake a difference in the meaning, I placed that punctuation in brackets. Watt wrote\noccasionally with long run-on sentences; these I chose to end at convenient spots,\nleaving sometimes incomplete sentences or adding a word, within brackets, to make\nthe text flow more evenly. In all cases, however, I sought to maintain the sense\nof the journal and to assure that every sentence completed a thought that added to\nthe meaning of the entire manuscript.<br />\nThe other changes which I made in Watt's journal were merely cosmetic in nature.\nPagination remained the same as in the copied text, except that I designated that\ntext found on the first side of the page as “r” and the second as “v.” I\nnumbered each side in this edition and began each side with the name of the place\n(in brackets) where or about which the text was originally written. In the text itself\nI used brackets to add missing parts of formal names and accepted spellings for places\nfound on contemporary maps of Guinea and Sierra Leone. In those situations where\nthe copier left a blank space in his copy, I noted these places with [blank]. Where\nthe copier made errors and marked through his text, I repeated his error, marked\nthrough it mechanically, and added [marked through in the text] immediately following\nthe error. I chose not to annotate this journal in the traditional manner because\nI was concerned that my annotations would become confused with Watt's writing, with\nthe copier's copying, and with any additions that may have been added to the manuscript\nover the past two hundred years. Instead of annotation, I introduced the journal\nand the conditions on the Windward Coast in the early 1790s in an introductory chapter\nand included elaborations concerning individuals, events, or items mentioned in the\ntext in the index.<br />\nMany shared in the labor which brought this journal to its present form. I first\nread the manuscript in 1968, struggling with the long and tedious script within the\nconfines of a research reading room. I knew that it was an important record and that\none day I would want to return to it in a more formal way. In 1981 Paul Hair of University\nof Liverpool, asked me if I would continue a transcription which one of his students\nhad started and I agreed to think about it. Perhaps sensing my reservation, Hair\nsent me a photocopy of the entire manuscript which with my microfilm copy set me\non a course that has consumed many hours and years. My daughter, Audrey, who was\nonly eleven years old at the time, became an adult in the shadow of Watt's journal,\nand in 1993 graduated from the University of Wisconsin-Madison with a concentration\nin African Studies, perhaps attesting to the long-term impact of the Watt project\non this household. Three departmental secretaries, Jan Larkin, Judy Sapio, and Marcella\nBergerson, became local Watt experts, typing and retyping numerous drafts before\nthe computer made that process easier. The list of students in the department who\nspent time checking spellings and deciphering words or sentences and constructing\nindexes which sometimes were meaningful, and sometimes not, perhaps cannot be reconstructed\nproperly. Of these the most important and latest were Rachel Breitsprecher and John\nLuster.<br />\nSeveral foundations and institutions provided financial assistance to support research\nthat made this edition possible. The National Endowment for the Humanities supported\ntravel to the 1981 International Sierra Leone Symposium at the University of Birmingham,\nwhere I read a paper on a related period in Guinean history and where Hair recruited\nme for this project. The University of Wisconsin-La Crosse and the University of\nWisconsin-La Crosse Foundation consistently funded research on topics which promised\na small readership, and I could not have continued my interest in this area without\ntheir valuable support. But perhaps most important, I appreciate the interest and\nsupport which I received from the Department of History at the University of Wisconsin-La\nCrosse, which provided secretarial help, supplies, travel support, and student help\nwhich made this project move forward. To all of these I owe my lasting thanks.</p>\n<p><strong>Bruce L. Mouser</strong><br />\n     Department of History<br />\nUniversity of Wisconsin-La Crosse</p>"
    },
    {
      "id": "pages-01",
      "file": "pages/01.html",
      "titre": "Northern Rivers of Sierra Leone, Physical Features",
      "html": "<h1>webFuuta<br />\n History</h1>\n<hr size=\"3\" />\n<h1> Journal of James Watt <br />\nExpedition to Timbo, Capital of the Fula Empire in 1794</h1>\n\n<table align=\"center\" border=\"0\" cellpadding=\"0\" cellspacing=\"2\" width=\"200\">\n<tr>\n\t<td width=\"80\" align=\"center\"></td>\n\t<td width=\"80\" align=\"center\"><a href=\"#chap:pages-02\"></a></td>\n</tr>\n</table>\n<p align=\"center\">\n<a href=\"#chap:pages-02\"><img src=\"/livres/watt/01.jpg\" height=\"1150\" width=\"800\" border=\"1\" alt=\"Map I: Northern Rivers of Sierra Leone, Physical Features\" /></a> </p>\n<p class=\"caption\">Map I: Northern Rivers of Sierra Leone, Physical Features </p>"
    },
    {
      "id": "pages-02",
      "file": "pages/02.html",
      "titre": "Route of the Watt Expedition, January-May 1794",
      "html": "<h1>webFuuta<br />\n History</h1>\n<hr size=\"3\" />\n<h1> Journal of James Watt <br />\nExpedition to Timbo, Capital of the Fula Empire in 1794</h1>\n<table align=\"center\" border=\"0\" cellpadding=\"0\" cellspacing=\"2\" width=\"200\">\n<tr>\n\t<td width=\"80\" align=\"center\"><a href=\"#chap:pages-01\"></a></td>\n\t<td width=\"80\" align=\"center\"></td>\n\t<td width=\"80\" align=\"center\"><a href=\"#chap:pages-03\"></a></td>\n</tr>\n</table>\n<p align=\"center\"><a href=\"#chap:pages-03\"><img src=\"/livres/watt/02.jpg\" height=\"1163\" width=\"800\" border=\"1\" alt=\"Map II - Route of the Watt Expedition, January-May 1794 \" /></a></p>\n<p class=\"caption\"> Map II: Route of the Watt Expedition, January-May 1794 </p>"
    },
    {
      "id": "pages-03",
      "file": "pages/03.html",
      "titre": "Rio Nunez Sector of the Watt Expedition, 31 January-13 February 1794",
      "html": "<h1>webFuuta<br />\n History</h1>\n<hr size=\"3\" />\n<h1> Journal of James Watt <br />\nExpedition to Timbo, Capital of the Fula Empire in 1794</h1>\n<table  align=\"center\" border=\"0\" cellpadding=\"0\" cellspacing=\"2\" width=\"200\">\n<tr>\n\t<td width=\"80\" align=\"center\"><a href=\"#chap:pages-02\"></a></td>\n\t<td width=\"80\" align=\"center\"></td>\n\t<td width=\"80\" align=\"center\"><a href=\"#chap:pages-04\"></a></td>\n</tr>\n</table>\n<p align=\"center\"><a href=\"#chap:pages-04\"><img src=\"/livres/watt/03.jpg\" height=\"550\" width=\"800\" border=\"1\" alt=\"Map A: Rio Nunez Sector of the Watt Expedition, 31 January-13 February 1794\" /></a></p>\n<p class=\"caption\">Map A: Rio Nunez Sector of the Watt Expedition, 31 January-13 February 1794 </p>"
    },
    {
      "id": "pages-04",
      "file": "pages/04.html",
      "titre": "Kouna/Koba Sector of the Watt Expedition, 13-19 February 1794",
      "html": "<h1>webFuuta<br />\n History</h1>\n<hr size=\"3\" />\n<h1> Journal of James Watt <br />\nExpedition to Timbo, Capital of the Fula Empire in 1794</h1>\n<table align=\"center\" border=\"0\" cellpadding=\"0\" cellspacing=\"2\" width=\"200\">\n<tr>\n\t<td width=\"80\" align=\"center\"><a href=\"#chap:pages-03\"></a></td>\n\t<td width=\"80\" align=\"center\"></td>\n\t<td width=\"80\" align=\"center\"><a href=\"#chap:pages-05\"></a></td>\n</tr>\n</table>\n<p align=\"center\"><a href=\"#chap:pages-05\"><img src=\"/livres/watt/04.jpg\" height=\"561\" width=\"830\" border=\"1\" alt=\"Map C: Kouna/Koba Sector of the Watt Expedition, 13-19 February 1794\" /></a></p>\n<p class=\"caption\">Map C: Kouna/Koba Sector of the Watt Expedition, 13-19 February 1794 </p>"
    },
    {
      "id": "pages-05",
      "file": "pages/05.html",
      "titre": "Labé Sector of the Watt Expedition, 19 February-2 March 1794",
      "html": "<h1>webFuuta<br />\n History</h1>\n<hr size=\"3\" />\n<h1> Journal of James Watt <br />\nExpedition to Timbo, Capital of the Fula Empire in 1794</h1>\n<table  align=\"center\" border=\"0\" cellpadding=\"0\" cellspacing=\"2\" width=\"200\">\n<tr>\n\t<td width=\"80\" align=\"center\"><a href=\"#chap:pages-04\"></a></td>\n\t<td width=\"80\" align=\"center\"></td>\n\t<td width=\"80\" align=\"center\"><a href=\"#chap:pages-06\"></a></td>\n</tr>\n</table>\n<p align=\"center\"><a href=\"#chap:pages-06\"><img src=\"/livres/watt/04.jpg\" height=\"561\" width=\"830\" border=\"1\" alt=\"Map C: Labé Sector of the Watt Expedition, 19 February-2 March 1794\" /></a></p>\n<p class=\"caption\">Map C: Labé Sector of the Watt Expedition, 19 February-2 March 1794</p>"
    },
    {
      "id": "pages-06",
      "file": "pages/06.html",
      "titre": "Timbo Sector of the Watt Expedition, 2-27 March 1794",
      "html": "<h1>webFuuta<br />\n History</h1>\n<hr size=\"3\" />\n<h1> Journal of James Watt <br />\nExpedition to Timbo, Capital of the Fula Empire in 1794</h1>\n\n<table  align=\"center\" border=\"0\" cellpadding=\"0\" cellspacing=\"2\" width=\"200\">\n<tr>\n\t<td width=\"80\" align=\"center\"><a href=\"#chap:pages-05\"></a></td>\n\t<td width=\"80\" align=\"center\"></td>\n\t<td width=\"80\" align=\"center\"><a href=\"#chap:pages-07\"></a></td>\n</tr>\n</table>\n<p align=\"center\"><a href=\"#chap:pages-07\"><img src=\"/livres/watt/06.jpg\" height=\"516\" width=\"741\" border=\"1\" alt=\"06\" /></a></p>\n<p class=\"notes\">Map D: Timbo Sector of the Watt Expedition, 2-27 March 1794 </p>"
    },
    {
      "id": "pages-07",
      "file": "pages/07.html",
      "titre": "Kalia/Santiguia Sector of the Watt Expedition, 27 March - 14 April 1794",
      "html": "<h1>webFuuta<br />\n History</h1>\n<hr size=\"3\" />\n<h1> Journal of James Watt <br />\nExpedition to Timbo, Capital of the Fula Empire in 1794</h1>\n<table align=\"center\" border=\"0\" cellpadding=\"0\" cellspacing=\"2\" width=\"200\">\n<tr>\n\t<td width=\"80\" align=\"center\"><a href=\"#chap:pages-06\"></a></td>\n\t<td width=\"80\" align=\"center\"></td>\n\t<td width=\"80\" align=\"center\"><a href=\"#chap:pages-08\"></a></td>\n</tr>\n</table>\n<p align=\"center\"><a href=\"#chap:pages-08\"><img src=\"/livres/watt/07.jpg\" height=\"579\" width=\"830\" border=\"1\" alt=\"Map E: Kalia-Santiguia Sector of the Watt Expedition, 27 March - 14 April 1794 \" /></a></p>\n<p class=\"notes\">Map E: Kalia/Santiguia Sector of the Watt Expedition, 27 March - 14 April 1794 </p>"
    },
    {
      "id": "pages-08",
      "file": "pages/08.html",
      "titre": "Santiguia/Bereira Sector of the Watt Expedition, 14 April-2 May 1794",
      "html": "<h1>webFuuta<br />\n History</h1>\n<hr size=\"3\" />\n<h1> Journal of James Watt <br />\nExpedition to Timbo, Capital of the Fula Empire in 1794</h1>\n\n<table align=\"center\" border=\"0\" cellpadding=\"0\" cellspacing=\"2\" width=\"200\">\n<tr>\n\t<td width=\"80\" align=\"center\"><a href=\"#chap:pages-07\"></a></td>\n\t<td width=\"80\" align=\"center\"></td>\n</tr>\n</table>\n<p align=\"center\"><a href=\"#chap:pages-01\"><img src=\"/livres/watt/08.jpg\" height=\"575\" width=\"830\" border=\"1\" alt=\"Map F: Santiguia-Bereira Sector of the Watt Expedition, 14 April-2 May 1794\" /></a></p>\n<p class=\"notes\">Map F: Santiguia/Bereira Sector of the Watt Expedition, 14 April-2 May 1794</p>"
    },
    {
      "id": "intro",
      "file": "intro.html",
      "titre": "Introduction",
      "html": "<h2>Introduction</h2>\n<p>The 1794 expedition to Timbo, capital of the Fula empire, by <strong>James Watt</strong> and <strong>Matthew\n     Winterbottom</strong> as agents of the Sierra Leone Company, came as a result of events\n     and circumstances on the Windward Coast which had been building over four years\n     and involved a number of participants. The Sierra Leone Company, a relatively\n     recent commercial entrant on the coast' had political and commercial objectives\n     which had become stalled by events beyond its control. Long-term resident traders\n     and those who acted as independents on this coast had problems of their own,\n     for they were adjusting to a new European war which interfered with normal commerce,\n     as well as to competition from the Sierra Leone Company and its agents; and\n     they were struggling to maintain marginal positions relative to local political\n     elites and growing African competition in trade. African groups, whether local\n     or long distant from the coast, were also players in this drama, for events\n     on the coast had disrupted traditional markets and interfered with access to\n     manufactures, kola, and salt. All parties were profoundly affected by the drama\n     that occurred between January and May of 1794.<br />\n     The most crucial of these participants was the Sierra Leone Company, which put\n     the expedition into motion in 1794. Between 1791, the year in which Parliament\n     chartered the Sierra Leone venture, and late 1793 the company's objectives and\n     fortune at Freetown fluctuated dramatically. Its objectives in 1791 were clear:     </p>\n<ul>\n     <li>To spread Christianity from its post on the coast</li>\n     <li>To promote trade in African\n     products, and </li>\n     <li>To oppose the slave trade1 </li>\n</ul>\n<p>But the charter granted the company neither exclusive rights to territory nor\n     a monopoly of trade at Sierra Leone, leaving slavers free access to the river\n     and to the company's settlement at Freetown 2. The company's directors expected\n     the company to expand its commerce into the river's hinterland, to wholesale\n     trade goods to neighboring merchants, and to grow cash crops, such as sugar,\n     cotton, tobacco, coffee, pineapples, pepper, coconuts, and rice. These products\n     in turn could be exported to England or would sustain and make the settlement\n     selfsufficient This latter objective, it was believed, would encourage neighboring\n     peoples also to grow cash crops, in effect to sell labor and the result of labor\n     rather than  slaves to the world market 3.<br />\n     Circumstances changed dramatically, however, with the appointment of <strong>John\n     Clarkson</strong>     as director of the enterprise at Sierra Leone and with the arrival of approximately\n     1190 liberated AfroAmericans from Nova Scotia in Canada in March 1792. A confused\n     form of administration for the settlement confounded Clarkson almost immediately\n     and resulted in disagreements with settlers over land rights and promises made\n     in Nova Scotia. Clarkson found the company's objectives of expanding trade into\n     the interior to be unrealistic and turned the settlement's attention instead\n     to the cultivation of crops to make it self-sufficient, an “agricultural\n     Mecca” of sorts 4.<br />\nOnly when problems of rents and distribution of lands to the settlers had been solved\nwould Clarkson be willing to return to the larger task of developing coastal and\nriver trade or of teaching Africans commercial habits which the company considered\nboth morally and ethically sound 5.<br />\nWhile Clarkson exhausted both time and energies trying to supervise the Nova Scotians\nand fulfill promises made to them before they left Canada, the company's directors\nin England were focusing on other issues, such as securing a profitable return on\ntheir £<strong>235,280</strong> investment made in 1791 6. Instead of gaining profits, investors saw\ntheir share capital declining steadily. Now they wanted a return on their investinent\nin the form of either cash crops or extended linkages to trading systems into the\ninterior. To achieve any of these objectives, Clarkson needed assistants who would\nhelp him control the Nova Scotians. The company, however, sent estate managers, most\nof whom had obtained experience operating plantations or business ventures in the\nCaribbean 7. In August 1792 Clarkson became governor and would soon be assisted by\n<strong>William Dawes</strong>, who had been a low-ranking officer of marines at Botany Bay, and <strong>Zachary\nMacaulay</strong>, who combined a commercial acumen learned in Jamaica with devotion to the\nanti-slave trade zeal of the company's directors 8. With such disparate leadership,\nthe company's venture appeared to be increasingly at risk.<br />\nAdding to the difficulties which resulted from conflicting objectives between Clarkson\nand the company directors were other problems which continued beyond the company's\nability to control. The presence of slave traders within a few miles of the company's\nsettlement at Freetown in 1792 continued to thwart the company's vision of legitimate\ncommerce and its future dominance in that trade 9. In the main branch of the Sierra\nLeone River was <strong>John Tilley</strong>'s factory on Bance Island. Bance had only one small settlement,\nAdam's town, a few houses, and a cemetery. This was the principal center of slaving\nactivity above Freetown on the river. Any slaver visiting its factory or leaving\nit would necessarily pass Freetown on its way to the sea, tempting Nova Scotians\nto join trades known to be successful on the coast 10.<br />\nCloser to Freetown was a prosperous French-operated factory on Gambia Island which\nwas administered by a <strong>Dr. Renaud</strong> 11. Both Renaud and Tilley were connected to larger\ntrading concerns in Britain or France, and both enjoyed the protection of trade which\nthese connections guaranteed. Had the Nova Scotians taken willingly to farming or\nlocal productions, the company's problems with the settlers and with Tilley and Renaud\nmight have been minimal. That was not, however, to be the case; instead, settlers\nsaw their success more securely tied to the river's commerce and to trade elsewhere\nalong the coast 12. Consequently, the company found it increasingly difficult to\nkeep watch over its Nova Scotian charges and to generate foodstuffs and cash crops\nsufficient to make the settlement self-sustaining 13.<br />\nWilliam Dawes, and indirectly his deputy Zachary Macaulay, were directed to revitalize\nthe settlement and return the company to its former purpose in coastal commerce,\nto sell wholesale goods to local traders, to produce cash crops which would replace\nslave trading as the principal avenue of capital accumulation for both settlers and\nlocal Africans, and to make the settlement self-sufficient. This new turn effectively\nrevived the expansionist vision of the company and brought it into potential conflict\nwith other forces on the coast. Dawes attempted to extend plantation agriculture\non Bullom Shore and on islands in the Sierra Leone estuary, following the lead of\nslavetraders who were actively growing cotton, sugar cane, tobacco, and rice on several\nof the neighboring islands 14.<br />\nWholesaling manufactures to neighboring traders was a good idea, if trade goods could\nbe obtained. Rumors of possible warfare between Britain and revolutionary France\ncirculated increasingly, and with fewer American vessels visiting the coast, supplies\nof trade goods became scarce. Increasingly the company found it necessary to spend\nmuch of its trade capital to purchase rice and cattle, necessities which kept the\nsettlement alive and under control. The prospects of expanding trade connections\ninto the African interior brightened, however, with the Houghton report to the African\nAssociation in 1792, and with the arrival in Freetown of an Islamic teacher from\nPort Loko, who invited the company to establish commercial contact with interior\nstates along international paths which crossed his territory 15.<br />\nThe declaration of war against Britain by France on February 1st, 1793 increased\nthe strains then present at Sierra Leone 16. John Clarkson had anticipated such a\nwar and had written to the <strong>Marquis de Lafayette</strong> in July 1792, asking him to use his\ninfluence to assure neutrality for the Sierra Leone Company should war commence 17.\nIndeed, the two Clarksons, John and his brother Thomas, were recognized as friendly\nto the French revolution and its ideas 18. British and French trade along the west\ncoast shrank late in 1792, with shippers reluctant to risk the loss of a cargo to\nprivateers who would look for an excuse to seize vessels as booty of war 19. For\nthe moment Freetown was secure, but declining trade goods meant that the settlement\nwould not be resupplied and might need to expend additional capital goods to maintain\nthe settlement. Cattle sources from the Gambia River were now gone as well 20.<br />\nThe outbreak of the war early in 1793 also produced stresses on neighboring slave\ntraders, who rejected neutrality, seeking instead to use the war as an opportunity\nfor expansion. Dr. Renaud on Gambia Island understood well his precarious position\nin the Sierra Leone River, surrounded as he was by British subjects, some of whom,\nlike John Tilley, had reason to settle old scores with him 21. Renaud appealed to\nGovernor Dawes for company protection, claiming a neutral stand in the Franco-British\nwar. Indeed, the company looked closely at Gambia Island as an area for potential\npurchase 22. While Tilley was reluctant to raid Renaud's property in the river, others\nwere not so disinclined. In June 1793 a British privateer seized one of Renaud's\nvessels and sold Renaud's cargo and several of his slaves and <em>grumettas</em> (free black\nlaborers) at Bance Island. Renaud's war canoes seized the privateer once he left\nBance, took him to Gambia Island, and sent word to Freetown to have the company mediate\nhis dispute with Tilley and the privateer. Tilley meanwhile prepared to attack Gambia.\nRenaud now proposed to place his factory under Sierra Leone Company custody and to\ngive up slavetrading altogether in return for company protection 23. Dawes replied\nthat the company would not risk its neutrality in the larger Franco-British war by\ntaking possession of French property, and instead asked that both the company and\nRenaud reaffirm their neutralities in the war by signing an agreement to that effect\n24.<br />\nTilley claimed no such neutrality, however, and his struggle with Renaud continued\nto fester. By late July both Tilley and Renaud, or their agents, reported regularly\nto Dawes and Deputy Governor Macaulay the despicable activities of the other, always\nrequesting that the company take sides in their continuing competition for economic\npreeminence 25. Renaud escalated his contest with Tilley in August by seizing a British\nslave ship, then releasing it to the company as a gesture of goodwill, while at the\nsame time threatening to destroy Bance Island. Tilley now demanded that the company\njoin him for a joint strike against Gambia; the company refused 26. In September,\nMacaulay met with Renaud, who proposed to abandon the Sierra Leone River within six\nweeks and to give Gambia Island to the company. Macaulay listened to the particulars\nof the dispute, but resolved nothing 27.<br />\nThe failure by either Dawes or Macaulay to resolve the continuing dispute between\nTilley and Renaud was only partially due to the company's desire to remain neutral\nin the Franco-British war of 1793. Another dimension to the Tilley-Renaud-Company\ndiscussion, however, was the possibility of a new source of cattle and rice which\nmight bypass Tilley and his subfactor at Port Loko as principal providers of these\nsupplies for the settlement. In <strong>November 1792</strong> an Islamic teacher from Port Loko had\nvisited Freetown and described the potential of a future international path between\nthe Fula empire and Freetown via Port Loko and the Scarcies 28. In September 1793\na headman from Port Loko visited Renaud's factory at Gambia and while there indicated\nhis interest in sending one or more of his own children to Freetown for an education\nand reported that the ruler of the Fula empire in the Futa Jalon was interested in\nabolishing the slave trade. The headman of Port Loko further invited the company\nto open its own factory in his town, a move which would open new markets for his\nown goods and free him from reliance on Tilley's agent, who operated a factory there\n29. For the company, this new suggestion placed again on its agenda its ultimate\nobjective of expanding trade into neighboring rivers and into linkages with interior\nsystems. To Tilley, this proposal elevated the stakes considerably in his struggle\nwith Renaud, raising the possibility that his share of trade between the settlement\nand the interior might be diminished significantly. Tilley was now on the defensive.<br />\nBy September 1793 Zachary Macaulay's vision of an expanded commercial network connecting\nthe company and its agents to trade in coastal rivers, hinterland towns, and perhaps\nat Timbo or farther beyond, was becoming formalized at Freetown. Since his arrival\nat the settlement, Macaulay had taken charge of providing the Afro-American settlers\nwith food and supplies, often at inflated prices and to his considerable profit,\nand had been willing to trade with slavetraders to succeed in this task. His successes\nbothered Maria Falconbridge, who described Macaulay as being too friendly with slavetraders,\na price she considered too costly for company success along the coast 30. Macaulay's\nplan was multifaceted. He planned to position company agents at factories at Port\nLoko and in the Rio Pongo farther to the north, to resolve long lasting differences\nbetween Iles de Los slavetraders and the settlement, and to send the company's best\nnegotiator directly to the Fula Empire to arrange an agreement between the company\nand distant suppliers of rice and cattle 31.<br />\nThe first of these objectives, to establish factories at Port Loko and in the Rio\nPongo, was already in the planning stages before the end of 1793. Port Loko was along\nan insecure path between Freetown and Timbo which crossed the territory of several\ngroups who might oppose an international path, thus making it necessary for armed\nFula warriors to escort traders and their cargoes to the coast. A factory at Port\nLoko also would endanger Tilley's commerce in the settlement's hinterland and might\ninterfere with Mandingo-Mandinka trade in salt and kola between Moria and interior\ntrading systems 32. Slave rebellions along the Futa/Scarcies corridor had disturbed\nthe area not long before, and Fula as well as Morian elites might wonder about the\nimpact of an international path on the uneasy calm which had come to the area 33.\nThe Mande state of Moria, with its capital at Forékariah, had consolidated\nits influence in the Melakori and Forékariah rivers a few years earlier, and\npolitical and commercial elites there were beginning to consider the company and\nits settlement at Freetown as an opportunity for trade in rice, hides, and cattle\nand perhaps also as an adversary in trade north of the British Settlement 34.<br />\nNot far from Moria and its Susu sister state of Sumbuya were the Iles de Los, which\nhad long served as important stations for European shippers in need of supplies,\ncargo, repair, or convalescence. The arrival of the Sierra Leone Company in 1791,\nas a strong advocate of the anti-slave trade, produced a dilemma of sorts for H.\nJackson and Richard Horrock who were the principal slave traders resident on the\nislands. Despite the obvious contradictions of company commerce with slavers, the\ncompany needed Jackson and Horrock and other slavers to provide them with goods from\nAmerican shippers frequenting the coast and with rice and cattle that often came\nfrom open paths at the Rio Pongo and the Rio Nunez 35. <strong>John\nOrmond</strong>, the most powerful\nand notorious slave trader in the Rio Pongo, was one of many slave traders who visited\nthe islands often, and it was while convalescing on these islands in 1791 that Ormond\nhad died 36. His death and a revolt by a large number of his slaves thrust the Rio\nPongo into political and economic confusion, and trade in the Rio Pongo did not recover\nfor nearly two years.<br />\nJohn Clarkson's policy that any slave or grumetta who sought the sanctuary of Freetown\nfrom his owner would be given company protection was a major source of conflict between\nthe Iles de Los traders and the settlement 37. This policy had caused problems for\nthe company with many traders, chiefs, and even ship captains along the coast, but\nthe most serious incident occurred in August 1793, when five <em>grumettas</em> attached to\nHorrock and Jackson, after delivering trade goods to Freetown, refused to return\nto the Iles de Los and requested sanctuary from the company 38. Later the <em>grumettas</em> explained that they had heard that Horrock was planning to retire because of the\ndepressed market which resulted from the Franco-British way and that he was planning\nto sell them at an early opportunity to an America-bound slaver 39. Both Horrock\nand Jackson demanded the return of their <em>grumettas</em>, and Macaulay, to whom responsibility\nfell for resolution of this dispute, complained bitterly of the dilemma that Clarkson's\npolicy had created for the company 40. Macaulay needed the support and friendship\nof slavers and slave shippers, not anxiety that their property might seek asylum\nin the settlement. Macaulay also needed the goodwill of chiefs to the north of Freetown,\nchiefs who only recently had suppressed slave rebellions 41. Hoffock's death in 1793\ndid nothing to resolve the problem, and the asylum issue, while anathema to the success\nof the company, continued to plague the company and the colony of Sierra Leone for\nyears to come 42.<br />\nThe other part of Macaulay's plan was to establish a factory in the Rio\nPongo and\nto send his best negotiator to Timbo in the Futa Jalon 43. The Rio Pongo and the\nRio Nunez to the north of it were centers of coastal trade to more than a dozen American,\nEuropean, Eurafrican and African traders located in the grasslands above the mangrove\nshorelines. These centers of trade, located at points where captains could anchor\ntheir vessels, served as terminals of long-distance trade between the Futa Jalon\nand the coast. Goods which came coastward from the interior included rice, hides,\nivory, gum, some gold, and of course the bearers of these goods, the surplus slaves\nwho would not be needed on the return trip into the interior. The paths connecting\nthe Rio Pongo to the interior commenced at Labé to the north and Timbo to\nthe south, and came together into a single path not too distant from the coast itself\n44. The southern path was less secure than the northern one, partly because of the\nslave rebellions which had characterized the Futa/Scarcies corridor after mid-century.\nThe northern path was outside Timbo control. The principal traders in the Rio Pongo\nwere the descendants of mixed Portuguese and Baga parentage, a few Susu traders\nwho took advantage of the presence of Europeans to provision slavers with rice and\nsupplies needed in the middle passage, and European or American traders and their\noffspring who dominated commerce in the river. John Ormond had been one of this group\nbefore his death in 1791, acting as a chief in his own right and serving as the Fula-sanctioned\nmerchant in the river. Ormond had maintained a representative at Timbo to look after\nhis interest in the interior and to keep him attuned to political changes which would\naffect political and commercial conditions on the coast.<br />\nThe Rio Nunez was clearly the more secure trading area for Europeans, partly because\nof the easy and wide estuary, and the absence of reefs or sandbars that could surprise\nthe unwary ship captain 46. Most captains hired a pilot at the Iles de Los to guide\nthem into the river and to the spot nearly thirty miles upstream where the grasslands\nbegan, where large numbers of Fula came with goods to trade, and where several long-established\nEuropeans and Eurafricans maintained factories. One could expect to find goods waiting\nto be bought and a ready market for any goods brought for sale. One could also expect\nhospitality, a chance to walk from factory to factory, visiting and catching up on\nnews of the coast. The food and drink were good, and if one avoided the rainy season,\nthe healthiness of the air was wonderful 47. Indeed, one of the factories would be\ncalled \"Bel-aire.\" <br />\nThe African landlords who owned the land here, the Nalus and the Landumans, were\npoorly organized to regulate either trade or the Europeans or to oppose the Fula\ntraders who came by the hundreds into their territories 48. The Fula considered the paths connecting factories to the interior <strong>as belonging to them</strong> and the landlords on the coast <strong>as lowly, as-yet-unconverted, subjects</strong> 49. As in the Pongo, the relationship of the Fula to coastal rulers was that of <strong>ruler to subject, or upper to lower</strong>, and that relationship would not change for the next half-century.<br />\nSierra Leone Company interest in passing through Nunez factories on their way into\nthe Futa Jalon early in the 1794 produced a dilemma for Nunez traders The quantity\nof trade goods available for sale to Fula caravans at coastal factories had fallen\ndrastically in consequence of the Franco-British war, and for a time in 1793 Fula\ncaravans dwindled during a period of political turmoil in the interior. By early\n1794, however, Fula caravans arrived in large numbers with rice, ivory, and hides.\nThe market for slaves had declined significantly as well, with the reduced visits\nby French and British traders and with the decision by France to declare slavery\nillegal in French territory 50. Prices for slaves plummeted, and the large quantities\nof rice coming coastward had few buyers, for rice comprised the principal food provided\nto slaves while aboard ship or during the middle passage 51. The company might be\npurchasing rice and cattle for its own consumption, but traders in the Nunez were\nuncertain. Macaulay was proposing an expedition through the Nunez, not a factory\nor company agent to be stationed there. The proposed expedition also presented an\nopportunity for Nunez traders to send agents to Labé and Timbo to watch the\nactivities of the company and report back to their superiors in the Nunez what the\ncompany was planning to do there. <strong>David Lawrence</strong>, a Eurafrican factor at Kissassi\non the Nunez, provided two guides to the expedition, and Mr. <strong>Fortune</strong> of Boké and\nJames Walker of <em>Walkaria</em> (Kocundy) likewise offered the services of loyal employees\nto assist the expedition and keep them apprised of events in the interior 52.<br />\nWhether the Fula had actually invited the company to come to Timbo is unclear from\nthe sources. Perhaps events just transpired and the company assumed that there had\nactually been an invitation tendered. In any case, Dawes and Macaulay carefully planned\nthe expedition and executed it between January and June in 1794. The leader of the\nexpedition would be James</p>"
    }
  ]
}